[
  {
    "no": 1731600753922,
    "name": "First Test User",
    "email": "firsttestuser@gmail.com",
    "website": "FirstTestWebsite",
    "message": "I want to test this form"
  },
  {
    "no": 1731602147105,
    "name": "Test part 2",
    "email": "Cloud@dat.me",
    "website": "http://cloud.vn",
    "message": "Test form validation"
  },
  {
    "no": 1731602496895,
    "name": "ReloadPage",
    "email": "reloadpage@gmail.com",
    "website": "http://after.submit",
    "message": "After submit"
  },
  {
    "no": 1731602537744,
    "name": "Submit form",
    "email": "helu@hu.ti",
    "website": "https://lala.lo",
    "message": "After submit once"
  },
  {
    "no": 1731602595482,
    "name": "Submit twice",
    "email": "tun@gmail.com",
    "website": "http://hclou.com",
    "message": "but fail"
  },
  {
    "no": 1731602748203,
    "name": "Isak",
    "email": "new.thang@hu.mp",
    "website": "click.bat",
    "message": "Sala righ as"
  },
  {
    "no": 1731603263860,
    "name": "Aorus Radeon RX 6750 XT GPU",
    "email": "tuana@yahoo.com",
    "website": "google.com",
    "message": "Hi everyone"
  },
  {
    "no": 1731603439735,
    "name": "Configure css",
    "email": "tuan@gmail.com",
    "website": "facebook.com",
    "message": "For spinner"
  },
  {
    "no": 1731603465296,
    "name": "Double click",
    "email": "tua@mass",
    "website": "facebook.com",
    "message": "On submit button"
  },
  {
    "no": 1731603489474,
    "name": "Clone",
    "email": "sadsad@giem",
    "website": "insta.data",
    "message": "Third times"
  }
]